django_ldap_user_registration/__init__.py
django_ldap_user_registration/local_settings.py
django_ldap_user_registration/settings.py
django_ldap_user_registration/urls.py
django_ldap_user_registration/wsgi.py
django_ldap_user_registration-1.1.dist-info/METADATA
django_ldap_user_registration-1.1.dist-info/RECORD
django_ldap_user_registration-1.1.dist-info/WHEEL
django_ldap_user_registration-1.1.dist-info/top_level.txt
dl_user/__init__.py
dl_user/admin.py
dl_user/apps.py
dl_user/context_processors.py
dl_user/exceptions.py
dl_user/forms.py
dl_user/ldap.py
dl_user/models.py
dl_user/passwd.py
dl_user/tests.py
dl_user/urls.py
dl_user/utils.py
dl_user/views.py
dl_user/migrations/0001_initial.py
dl_user/migrations/0002_userregistrationrecord.py
dl_user/migrations/0003_auto_20180710_1347.py
dl_user/migrations/0004_auto_20180712_1254.py
dl_user/migrations/0005_auto_20180712_1308.py
dl_user/migrations/0006_userregistrationrecord_ldap_password.py
dl_user/migrations/0007_userregistrationrecord_department.py
dl_user/migrations/__init__.py
dl_user/static/dl_user/styles.css
dl_user/templates/dl_user/index.html
dl_user/templates/dl_user/password_edit.html
dl_user/templates/dl_user/password_edit_success.html
dl_user/templates/dl_user/password_reset.html
dl_user/templates/dl_user/password_reset_success.html
dl_user/templates/dl_user/register.html
dl_user/templates/dl_user/register_activate_success.html
dl_user/templates/dl_user/register_success.html
user/__init__.py
user/admin.py
user/apps.py
user/context_processors.py
user/exceptions.py
user/forms.py
user/ldap.py
user/models.py
user/passwd.py
user/tests.py
user/urls.py
user/utils.py
user/views.py
user/migrations/0001_initial.py
user/migrations/0002_userregistrationrecord.py
user/migrations/0003_auto_20180710_1347.py
user/migrations/0004_auto_20180712_1254.py
user/migrations/0005_auto_20180712_1308.py
user/migrations/0006_userregistrationrecord_ldap_password.py
user/migrations/0007_userregistrationrecord_department.py
user/migrations/__init__.py
user/static/user/styles.css
user/templates/user/index.html
user/templates/user/password_edit.html
