Metadata-Version: 2.1
Name: django-ldap-user-registration
Version: 1.1
Summary: A Django web front-end that provides user registration and password reset to an LDAP server.
Home-page: https://github.com/KENET-KE/django-ldap-user-registration/
Author: Ronald Osure
Author-email: sureronald@gmail.com
License: GPL v3
Keywords: django ldap registration password reset idp federation catch-all
Platform: UNKNOWN
Classifier: Environment :: Web Environment
Classifier: Framework :: Django
Classifier: Framework :: Django :: 2.0
Classifier: Framework :: Django :: 2.1
Classifier: Development Status :: 4 - Beta
Classifier: Intended Audience :: Developers
Classifier: License :: OSI Approved :: GNU General Public License (GPL)
Classifier: Operating System :: OS Independent
Classifier: Programming Language :: Python
Classifier: Programming Language :: Python :: 3.5
Classifier: Programming Language :: Python :: 3.6
Classifier: Topic :: Internet :: WWW/HTTP
Classifier: Topic :: Internet :: WWW/HTTP :: Dynamic Content
Requires-Dist: Django (>=2.0)
Requires-Dist: python-ldap
Requires-Dist: django-bootstrap3
Requires-Dist: django-anymail
Requires-Dist: django-crispy-forms
